myhand/README.md
myhand/__init__.py
myhand/autoassist.py
myhand/autobuilder.py
myhand/automath.py
myhand/autoretriever.py
myhand/chatgpt.py
myhand/codey.py
myhand/commandprompt.py
myhand/config.py
myhand/eTextEdit.py
myhand/geminipro.py
myhand/geminiprovision.py
myhand/health_check.py
myhand/main.py
myhand/ollamachat.py
myhand/package_name.txt
myhand/palm2.py
myhand/requirements.txt
myhand/systemtray.py
myhand/audio/notification1.mp3
myhand/audio/notification1_mild.mp3
myhand/audio/notification2.mp3
myhand/audio/notification2_mild.mp3
myhand/files/Readme.md
myhand/history/Readme.md
myhand/icons/CyberTask.ico
myhand/icons/CyberTask.png
myhand/icons/GeminiPro.ico
myhand/icons/GeminiPro.png
myhand/icons/LetMeDoIt.ico
myhand/icons/LetMeDoIt.png
myhand/icons/MyHand.ico
myhand/icons/MyHand.png
myhand/icons/TaskWiz.ico
myhand/icons/TaskWiz.png
myhand/icons/systemtray.ico
myhand/icons/systemtray.png
myhand/macOS_service/LetMeDoIt_Download_workflow/Contents/Info.plist
myhand/macOS_service/LetMeDoIt_Download_workflow/Contents/document.wflow
myhand/macOS_service/LetMeDoIt_Download_workflow/Contents/QuickLook/Thumbnail.png
myhand/macOS_service/LetMeDoIt_Explanation_workflow/Contents/Info.plist
myhand/macOS_service/LetMeDoIt_Explanation_workflow/Contents/document.wflow
myhand/macOS_service/LetMeDoIt_Explanation_workflow/Contents/QuickLook/Thumbnail.png
myhand/macOS_service/LetMeDoIt_Files_workflow/Contents/Info.plist
myhand/macOS_service/LetMeDoIt_Files_workflow/Contents/document.wflow
myhand/macOS_service/LetMeDoIt_Files_workflow/Contents/QuickLook/Thumbnail.png
myhand/macOS_service/LetMeDoIt_Pronounce_workflow/Contents/Info.plist
myhand/macOS_service/LetMeDoIt_Pronounce_workflow/Contents/document.wflow
myhand/macOS_service/LetMeDoIt_Pronounce_workflow/Contents/QuickLook/Thumbnail.png
myhand/macOS_service/LetMeDoIt_Summary_workflow/Contents/Info.plist
myhand/macOS_service/LetMeDoIt_Summary_workflow/Contents/document.wflow
myhand-2.1.61.dist-info/METADATA
myhand-2.1.61.dist-info/WHEEL
myhand-2.1.61.dist-info/entry_points.txt
myhand-2.1.61.dist-info/top_level.txt
myhand-2.1.61.dist-info/RECORD
