Metadata-Version: 2.1
Name: myhand
Version: 2.1.61
Summary: MyHand Bot, an advanced AI assistant, leveraging the capabilities of ChatGPT API, Gemini Pro and AutoGen, capable of engaging in conversations, executing codes with auto-healing, and assisting you with a wide range of tasks on your local devices.
Home-page: https://letmedoit.ai
Author: Eliran Wong
Author-email: support@letmedoit.ai
License: GNU General Public License (GPL)
Project-URL: Source, https://github.com/eliranwong/letmedoit
Project-URL: Tracker, https://github.com/eliranwong/letmedoit/issues
Project-URL: Documentation, https://github.com/eliranwong/letmedoit/wiki
Project-URL: Funding, https://www.paypal.me/letmedoitai
Keywords: ai assistant openai chatgpt gemini autogen rag interpreter auto-heal
Platform: UNKNOWN
Classifier: Development Status :: 5 - Production/Stable
Classifier: Intended Audience :: End Users/Desktop
Classifier: Topic :: Utilities
Classifier: Topic :: Scientific/Engineering :: Artificial Intelligence
Classifier: Topic :: Software Development :: Build Tools
Classifier: License :: OSI Approved :: GNU General Public License v3 or later (GPLv3+)
Classifier: Programming Language :: Python :: 3.8
Classifier: Programming Language :: Python :: 3.9
Classifier: Programming Language :: Python :: 3.10
Classifier: Programming Language :: Python :: 3.11
Requires-Python: >=3.8, <3.12
Requires-Dist: PyMuPDF
Requires-Dist: PySide6
Requires-Dist: Pygments
Requires-Dist: SpeechRecognition
Requires-Dist: apsw
Requires-Dist: argparse
Requires-Dist: art
Requires-Dist: chromadb
Requires-Dist: colorama
Requires-Dist: datetime
Requires-Dist: docker
Requires-Dist: einops
Requires-Dist: elevenlabs ==0.3.0b0
Requires-Dist: feedparser
Requires-Dist: folium
Requires-Dist: gTTS
Requires-Dist: geocoder
Requires-Dist: google-cloud-aiplatform ==1.42.1
Requires-Dist: google-cloud-speech
Requires-Dist: google-cloud-texttospeech
Requires-Dist: googlesearch-python
Requires-Dist: html2text
Requires-Dist: netifaces
Requires-Dist: numpy
Requires-Dist: ollama
Requires-Dist: openai-whisper
Requires-Dist: openai ==1.12.0
Requires-Dist: pendulum
Requires-Dist: pillow
Requires-Dist: prompt-toolkit
Requires-Dist: pyautogen[autobuild,mathchat,retrievechat] ==0.2.14
Requires-Dist: pygame
Requires-Dist: pypdf
Requires-Dist: pyperclip
Requires-Dist: pywhatkit
Requires-Dist: qrcode
Requires-Dist: rembg
Requires-Dist: requests
Requires-Dist: seaborn[stats]
Requires-Dist: sentence-transformers
Requires-Dist: setuptools-rust
Requires-Dist: sounddevice
Requires-Dist: soundfile
Requires-Dist: sympy
Requires-Dist: tiktoken
Requires-Dist: torch ==2.2.1
Requires-Dist: torchvision ==0.17.1
Requires-Dist: transformers ==4.38.1
Requires-Dist: unstructured[all-docs]
Requires-Dist: yfinance
Requires-Dist: yt-dlp
